{"metadata": {"schema_version": "0.2", "title": "None", "source_filename": "Q4_1fdxsFbnsX4_0.mid", "source_format": "midi"}, "resolution": 384, "tempos": [{"time": 0, "qpm": 120.0}], "time_signatures": [{"time": 0, "numerator": 4, "denominator": 4}], "annotations": [{"time": 0, "annotation": {"emo_class": "4", "YouTube_ID": "1fdxsFbnsX4", "seg_id": "0"}}], "tracks": [{"program": 0, "is_drum": false, "notes": [{"time": 32, "pitch": 55, "duration": 845, "velocity": 40}, {"time": 241, "pitch": 62, "duration": 404, "velocity": 55}, {"time": 449, "pitch": 60, "duration": 422, "velocity": 55}, {"time": 656, "pitch": 62, "duration": 227, "velocity": 54}, {"time": 865, "pitch": 59, "duration": 854, "velocity": 57}, {"time": 1075, "pitch": 62, "duration": 407, "velocity": 53}, {"time": 1273, "pitch": 57, "duration": 444, "velocity": 55}, {"time": 1488, "pitch": 62, "duration": 233, "velocity": 44}, {"time": 1684, "pitch": 55, "duration": 858, "velocity": 38}, {"time": 1893, "pitch": 62, "duration": 411, "velocity": 53}, {"time": 2107, "pitch": 60, "duration": 415, "velocity": 53}, {"time": 2309, "pitch": 62, "duration": 211, "velocity": 51}, {"time": 2521, "pitch": 59, "duration": 827, "velocity": 52}, {"time": 2715, "pitch": 62, "duration": 410, "velocity": 51}, {"time": 2927, "pitch": 57, "duration": 422, "velocity": 43}, {"time": 3135, "pitch": 62, "duration": 212, "velocity": 41}, {"time": 3343, "pitch": 55, "duration": 865, "velocity": 35}, {"time": 3546, "pitch": 62, "duration": 294, "velocity": 52}, {"time": 3753, "pitch": 60, "duration": 437, "velocity": 52}, {"time": 3959, "pitch": 62, "duration": 232, "velocity": 51}, {"time": 4163, "pitch": 59, "duration": 839, "velocity": 54}, {"time": 4366, "pitch": 62, "duration": 410, "velocity": 51}, {"time": 4575, "pitch": 57, "duration": 429, "velocity": 53}, {"time": 4782, "pitch": 62, "duration": 222, "velocity": 42}, {"time": 4981, "pitch": 55, "duration": 1769, "velocity": 37}, {"time": 5194, "pitch": 62, "duration": 397, "velocity": 44}, {"time": 5396, "pitch": 60, "duration": 437, "velocity": 53}, {"time": 5597, "pitch": 62, "duration": 237, "velocity": 44}, {"time": 5825, "pitch": 59, "duration": 922, "velocity": 44}, {"time": 6045, "pitch": 62, "duration": 700, "velocity": 44}, {"time": 6277, "pitch": 57, "duration": 469, "velocity": 44}, {"time": 6783, "pitch": 83, "duration": 1096, "velocity": 80}, {"time": 6808, "pitch": 55, "duration": 1663, "velocity": 56}, {"time": 6852, "pitch": 81, "duration": 1634, "velocity": 87}, {"time": 7030, "pitch": 62, "duration": 411, "velocity": 56}, {"time": 7251, "pitch": 60, "duration": 1243, "velocity": 46}, {"time": 7451, "pitch": 62, "duration": 405, "velocity": 56}, {"time": 7655, "pitch": 59, "duration": 828, "velocity": 51}, {"time": 7656, "pitch": 74, "duration": 1944, "velocity": 76}, {"time": 7860, "pitch": 62, "duration": 411, "velocity": 48}, {"time": 8060, "pitch": 57, "duration": 423, "velocity": 54}, {"time": 8276, "pitch": 62, "duration": 206, "velocity": 48}, {"time": 8476, "pitch": 55, "duration": 1638, "velocity": 38}, {"time": 8684, "pitch": 62, "duration": 401, "velocity": 45}, {"time": 8893, "pitch": 60, "duration": 1229, "velocity": 46}, {"time": 9090, "pitch": 62, "duration": 410, "velocity": 45}, {"time": 9298, "pitch": 59, "duration": 823, "velocity": 59}, {"time": 9504, "pitch": 62, "duration": 410, "velocity": 47}, {"time": 9709, "pitch": 57, "duration": 412, "velocity": 57}, {"time": 9923, "pitch": 62, "duration": 197, "velocity": 48}, {"time": 10125, "pitch": 55, "duration": 434, "velocity": 63}, {"time": 10125, "pitch": 67, "duration": 431, "velocity": 74}, {"time": 10334, "pitch": 60, "duration": 222, "velocity": 57}, {"time": 10334, "pitch": 69, "duration": 221, "velocity": 76}, {"time": 10538, "pitch": 71, "duration": 413, "velocity": 83}, {"time": 10540, "pitch": 62, "duration": 411, "velocity": 59}, {"time": 10747, "pitch": 57, "duration": 201, "velocity": 61}, {"time": 10747, "pitch": 72, "duration": 201, "velocity": 77}, {"time": 10961, "pitch": 71, "duration": 425, "velocity": 81}, {"time": 10962, "pitch": 62, "duration": 419, "velocity": 58}, {"time": 11163, "pitch": 60, "duration": 223, "velocity": 56}, {"time": 11164, "pitch": 69, "duration": 222, "velocity": 73}, {"time": 11385, "pitch": 59, "duration": 193, "velocity": 52}, {"time": 11387, "pitch": 74, "duration": 924, "velocity": 69}, {"time": 11580, "pitch": 62, "duration": 231, "velocity": 46}, {"time": 11785, "pitch": 55, "duration": 833, "velocity": 42}, {"time": 11997, "pitch": 62, "duration": 194, "velocity": 47}, {"time": 12189, "pitch": 60, "duration": 434, "velocity": 59}, {"time": 12397, "pitch": 62, "duration": 225, "velocity": 48}, {"time": 12606, "pitch": 59, "duration": 327, "velocity": 61}, {"time": 12809, "pitch": 62, "duration": 285, "velocity": 48}, {"time": 13013, "pitch": 57, "duration": 441, "velocity": 59}, {"time": 13222, "pitch": 83, "duration": 235, "velocity": 80}, {"time": 13226, "pitch": 62, "duration": 228, "velocity": 47}, {"time": 13312, "pitch": 81, "duration": 128, "velocity": 79}, {"time": 13367, "pitch": 79, "duration": 91, "velocity": 81}, {"time": 13449, "pitch": 55, "duration": 820, "velocity": 57}, {"time": 13451, "pitch": 81, "duration": 864, "velocity": 77}, {"time": 13656, "pitch": 62, "duration": 398, "velocity": 57}, {"time": 13861, "pitch": 60, "duration": 427, "velocity": 56}, {"time": 14061, "pitch": 62, "duration": 235, "velocity": 55}, {"time": 14142, "pitch": 83, "duration": 152, "velocity": 79}, {"time": 14258, "pitch": 59, "duration": 824, "velocity": 44}, {"time": 14258, "pitch": 74, "duration": 826, "velocity": 70}, {"time": 14460, "pitch": 62, "duration": 408, "velocity": 54}, {"time": 14657, "pitch": 57, "duration": 427, "velocity": 44}, {"time": 14874, "pitch": 62, "duration": 211, "velocity": 46}, {"time": 15073, "pitch": 55, "duration": 839, "velocity": 40}, {"time": 15282, "pitch": 62, "duration": 354, "velocity": 44}, {"time": 15489, "pitch": 60, "duration": 430, "velocity": 56}, {"time": 15694, "pitch": 62, "duration": 224, "velocity": 46}, {"time": 15901, "pitch": 59, "duration": 748, "velocity": 57}, {"time": 16107, "pitch": 62, "duration": 412, "velocity": 54}, {"time": 16307, "pitch": 57, "duration": 346, "velocity": 50}, {"time": 16524, "pitch": 62, "duration": 129, "velocity": 45}, {"time": 16647, "pitch": 67, "duration": 3367, "velocity": 72}, {"time": 16713, "pitch": 79, "duration": 2671, "velocity": 77}, {"time": 16942, "pitch": 62, "duration": 407, "velocity": 46}, {"time": 17144, "pitch": 60, "duration": 446, "velocity": 57}, {"time": 17354, "pitch": 62, "duration": 235, "velocity": 58}, {"time": 17565, "pitch": 59, "duration": 801, "velocity": 59}, {"time": 17759, "pitch": 62, "duration": 396, "velocity": 59}, {"time": 17963, "pitch": 57, "duration": 403, "velocity": 59}, {"time": 18166, "pitch": 62, "duration": 200, "velocity": 48}, {"time": 18368, "pitch": 55, "duration": 1656, "velocity": 54}, {"time": 18588, "pitch": 62, "duration": 404, "velocity": 51}, {"time": 18787, "pitch": 60, "duration": 1235, "velocity": 59}, {"time": 18996, "pitch": 62, "duration": 396, "velocity": 48}, {"time": 19199, "pitch": 59, "duration": 821, "velocity": 60}, {"time": 19396, "pitch": 62, "duration": 418, "velocity": 46}, {"time": 19604, "pitch": 57, "duration": 417, "velocity": 47}, {"time": 19822, "pitch": 62, "duration": 198, "velocity": 47}, {"time": 19985, "pitch": 72, "duration": 144, "velocity": 74}, {"time": 20005, "pitch": 41, "duration": 9, "velocity": 43}, {"time": 20030, "pitch": 53, "duration": 1627, "velocity": 55}, {"time": 20032, "pitch": 71, "duration": 846, "velocity": 81}, {"time": 20238, "pitch": 60, "duration": 405, "velocity": 49}, {"time": 20436, "pitch": 59, "duration": 442, "velocity": 60}, {"time": 20648, "pitch": 60, "duration": 231, "velocity": 60}, {"time": 20858, "pitch": 57, "duration": 817, "velocity": 59}, {"time": 20864, "pitch": 69, "duration": 1899, "velocity": 70}, {"time": 21068, "pitch": 60, "duration": 389, "velocity": 55}, {"time": 21261, "pitch": 55, "duration": 414, "velocity": 42}, {"time": 21462, "pitch": 60, "duration": 213, "velocity": 49}, {"time": 21669, "pitch": 53, "duration": 610, "velocity": 45}, {"time": 21881, "pitch": 60, "duration": 382, "velocity": 57}, {"time": 22077, "pitch": 59, "duration": 187, "velocity": 46}], "annotations": [{"time": 92, "annotation": {"number": 64, "value": 127}, "group": "control_change"}, {"time": 875, "annotation": {"number": 64, "value": 0}, "group": "control_change"}, {"time": 1021, "annotation": {"number": 64, "value": 127}, "group": "control_change"}, {"time": 1716, "annotation": {"number": 64, "value": 0}, "group": "control_change"}, {"time": 1889, "annotation": {"number": 64, "value": 127}, "group": "control_change"}, {"time": 2523, "annotation": {"number": 64, "value": 0}, "group": "control_change"}, {"time": 2703, "annotation": {"number": 64, "value": 127}, "group": "control_change"}, {"time": 3343, "annotation": {"number": 64, "value": 0}, "group": "control_change"}, {"time": 3548, "annotation": {"number": 64, "value": 127}, "group": "control_change"}, {"time": 4179, "annotation": {"number": 64, "value": 0}, "group": "control_change"}, {"time": 4270, "annotation": {"number": 64, "value": 127}, "group": "control_change"}, {"time": 4995, "annotation": {"number": 64, "value": 0}, "group": "control_change"}, {"time": 5053, "annotation": {"number": 64, "value": 127}, "group": "control_change"}, {"time": 5833, "annotation": {"number": 64, "value": 0}, "group": "control_change"}, {"time": 5952, "annotation": {"number": 64, "value": 127}, "group": "control_change"}, {"time": 6744, "annotation": {"number": 64, "value": 0}, "group": "control_change"}, {"time": 6819, "annotation": {"number": 64, "value": 127}, "group": "control_change"}, {"time": 8482, "annotation": {"number": 64, "value": 0}, "group": "control_change"}, {"time": 8555, "annotation": {"number": 64, "value": 127}, "group": "control_change"}, {"time": 10130, "annotation": {"number": 64, "value": 0}, "group": "control_change"}, {"time": 10199, "annotation": {"number": 64, "value": 127}, "group": "control_change"}, {"time": 10558, "annotation": {"number": 64, "value": 0}, "group": "control_change"}, {"time": 10636, "annotation": {"number": 64, "value": 127}, "group": "control_change"}, {"time": 10956, "annotation": {"number": 64, "value": 0}, "group": "control_change"}, {"time": 11020, "annotation": {"number": 64, "value": 127}, "group": "control_change"}, {"time": 11387, "annotation": {"number": 64, "value": 0}, "group": "control_change"}, {"time": 11481, "annotation": {"number": 64, "value": 127}, "group": "control_change"}, {"time": 11809, "annotation": {"number": 64, "value": 0}, "group": "control_change"}, {"time": 11904, "annotation": {"number": 64, "value": 127}, "group": "control_change"}, {"time": 12185, "annotation": {"number": 64, "value": 0}, "group": "control_change"}, {"time": 12234, "annotation": {"number": 64, "value": 127}, "group": "control_change"}, {"time": 12623, "annotation": {"number": 64, "value": 0}, "group": "control_change"}, {"time": 12764, "annotation": {"number": 64, "value": 127}, "group": "control_change"}, {"time": 13051, "annotation": {"number": 64, "value": 0}, "group": "control_change"}, {"time": 13079, "annotation": {"number": 64, "value": 127}, "group": "control_change"}, {"time": 13452, "annotation": {"number": 64, "value": 0}, "group": "control_change"}, {"time": 13570, "annotation": {"number": 64, "value": 127}, "group": "control_change"}, {"time": 14301, "annotation": {"number": 64, "value": 0}, "group": "control_change"}, {"time": 14423, "annotation": {"number": 64, "value": 127}, "group": "control_change"}, {"time": 15080, "annotation": {"number": 64, "value": 0}, "group": "control_change"}, {"time": 15144, "annotation": {"number": 64, "value": 127}, "group": "control_change"}, {"time": 15916, "annotation": {"number": 64, "value": 0}, "group": "control_change"}, {"time": 16035, "annotation": {"number": 64, "value": 127}, "group": "control_change"}, {"time": 16661, "annotation": {"number": 64, "value": 0}, "group": "control_change"}, {"time": 16719, "annotation": {"number": 64, "value": 127}, "group": "control_change"}, {"time": 17587, "annotation": {"number": 64, "value": 0}, "group": "control_change"}, {"time": 17664, "annotation": {"number": 64, "value": 127}, "group": "control_change"}, {"time": 18365, "annotation": {"number": 64, "value": 0}, "group": "control_change"}, {"time": 18462, "annotation": {"number": 64, "value": 127}, "group": "control_change"}, {"time": 20024, "annotation": {"number": 64, "value": 0}, "group": "control_change"}, {"time": 20160, "annotation": {"number": 64, "value": 127}, "group": "control_change"}, {"time": 20871, "annotation": {"number": 64, "value": 0}, "group": "control_change"}, {"time": 20958, "annotation": {"number": 64, "value": 127}, "group": "control_change"}, {"time": 21670, "annotation": {"number": 64, "value": 0}, "group": "control_change"}, {"time": 21757, "annotation": {"number": 64, "value": 127}, "group": "control_change"}, {"time": 22261, "annotation": {"number": 64, "value": 0}, "group": "control_change"}]}]}