{"metadata": {"schema_version": "0.2", "title": "None", "source_filename": "Q4_8TYY0qG-KOw_0.mid", "source_format": "midi"}, "resolution": 384, "tempos": [{"time": 0, "qpm": 120.0}], "time_signatures": [{"time": 0, "numerator": 4, "denominator": 4}], "annotations": [{"time": 0, "annotation": {"emo_class": "4", "YouTube_ID": "8TYY0qG-KOw", "seg_id": "0"}}], "tracks": [{"program": 0, "is_drum": false, "notes": [{"time": 700, "pitch": 70, "duration": 175, "velocity": 68}, {"time": 880, "pitch": 66, "duration": 1393, "velocity": 51}, {"time": 883, "pitch": 70, "duration": 1221, "velocity": 49}, {"time": 1056, "pitch": 42, "duration": 1409, "velocity": 58}, {"time": 1056, "pitch": 61, "duration": 879, "velocity": 62}, {"time": 1217, "pitch": 49, "duration": 1247, "velocity": 63}, {"time": 1395, "pitch": 54, "duration": 709, "velocity": 74}, {"time": 1570, "pitch": 68, "duration": 357, "velocity": 53}, {"time": 1571, "pitch": 56, "duration": 892, "velocity": 61}, {"time": 1735, "pitch": 58, "duration": 2158, "velocity": 60}, {"time": 1936, "pitch": 68, "duration": 513, "velocity": 51}, {"time": 1939, "pitch": 61, "duration": 334, "velocity": 60}, {"time": 2110, "pitch": 54, "duration": 862, "velocity": 59}, {"time": 2111, "pitch": 70, "duration": 169, "velocity": 84}, {"time": 2282, "pitch": 61, "duration": 167, "velocity": 43}, {"time": 2284, "pitch": 66, "duration": 1402, "velocity": 51}, {"time": 2286, "pitch": 70, "duration": 1231, "velocity": 54}, {"time": 2454, "pitch": 61, "duration": 886, "velocity": 63}, {"time": 2455, "pitch": 68, "duration": 1403, "velocity": 73}, {"time": 2459, "pitch": 39, "duration": 1399, "velocity": 63}, {"time": 2622, "pitch": 46, "duration": 1236, "velocity": 62}, {"time": 2808, "pitch": 51, "duration": 709, "velocity": 51}, {"time": 2978, "pitch": 54, "duration": 2382, "velocity": 64}, {"time": 3346, "pitch": 61, "duration": 524, "velocity": 63}, {"time": 3525, "pitch": 70, "duration": 169, "velocity": 82}, {"time": 3527, "pitch": 51, "duration": 330, "velocity": 51}, {"time": 3696, "pitch": 66, "duration": 167, "velocity": 60}, {"time": 3698, "pitch": 70, "duration": 165, "velocity": 58}, {"time": 3873, "pitch": 37, "duration": 1407, "velocity": 66}, {"time": 3874, "pitch": 61, "duration": 872, "velocity": 68}, {"time": 3874, "pitch": 66, "duration": 1217, "velocity": 81}, {"time": 3874, "pitch": 70, "duration": 1048, "velocity": 62}, {"time": 4047, "pitch": 44, "duration": 1231, "velocity": 53}, {"time": 4223, "pitch": 49, "duration": 707, "velocity": 56}, {"time": 4393, "pitch": 51, "duration": 168, "velocity": 74}, {"time": 4567, "pitch": 51, "duration": 713, "velocity": 45}, {"time": 4750, "pitch": 61, "duration": 518, "velocity": 56}, {"time": 4934, "pitch": 70, "duration": 347, "velocity": 87}, {"time": 4935, "pitch": 49, "duration": 346, "velocity": 57}, {"time": 5101, "pitch": 66, "duration": 167, "velocity": 58}, {"time": 5277, "pitch": 66, "duration": 1227, "velocity": 67}, {"time": 5278, "pitch": 35, "duration": 1402, "velocity": 62}, {"time": 5279, "pitch": 61, "duration": 350, "velocity": 70}, {"time": 5450, "pitch": 42, "duration": 1223, "velocity": 53}, {"time": 5633, "pitch": 47, "duration": 695, "velocity": 61}, {"time": 5634, "pitch": 61, "duration": 172, "velocity": 60}, {"time": 5809, "pitch": 68, "duration": 342, "velocity": 79}, {"time": 5810, "pitch": 61, "duration": 341, "velocity": 66}, {"time": 6155, "pitch": 68, "duration": 334, "velocity": 53}, {"time": 6159, "pitch": 61, "duration": 514, "velocity": 62}, {"time": 6336, "pitch": 47, "duration": 343, "velocity": 61}, {"time": 6338, "pitch": 70, "duration": 174, "velocity": 83}, {"time": 6498, "pitch": 68, "duration": 182, "velocity": 49}, {"time": 6509, "pitch": 66, "duration": 1409, "velocity": 51}, {"time": 6517, "pitch": 70, "duration": 302, "velocity": 48}, {"time": 6679, "pitch": 61, "duration": 171, "velocity": 66}, {"time": 6681, "pitch": 42, "duration": 1052, "velocity": 67}, {"time": 6827, "pitch": 70, "duration": 906, "velocity": 42}, {"time": 6856, "pitch": 49, "duration": 1214, "velocity": 61}, {"time": 6857, "pitch": 61, "duration": 700, "velocity": 56}, {"time": 7048, "pitch": 54, "duration": 685, "velocity": 60}, {"time": 7213, "pitch": 56, "duration": 856, "velocity": 58}, {"time": 7214, "pitch": 68, "duration": 857, "velocity": 51}, {"time": 7389, "pitch": 58, "duration": 680, "velocity": 72}, {"time": 7563, "pitch": 61, "duration": 508, "velocity": 63}, {"time": 7740, "pitch": 54, "duration": 330, "velocity": 62}, {"time": 7742, "pitch": 42, "duration": 327, "velocity": 58}, {"time": 7742, "pitch": 70, "duration": 675, "velocity": 81}, {"time": 7922, "pitch": 66, "duration": 979, "velocity": 57}, {"time": 8078, "pitch": 68, "duration": 1330, "velocity": 71}, {"time": 8082, "pitch": 61, "duration": 1437, "velocity": 63}, {"time": 8083, "pitch": 39, "duration": 1435, "velocity": 65}, {"time": 8253, "pitch": 46, "duration": 1264, "velocity": 58}, {"time": 8445, "pitch": 51, "duration": 709, "velocity": 60}, {"time": 8618, "pitch": 54, "duration": 406, "velocity": 75}, {"time": 8905, "pitch": 66, "duration": 441, "velocity": 21}, {"time": 9034, "pitch": 54, "duration": 485, "velocity": 44}, {"time": 9158, "pitch": 51, "duration": 360, "velocity": 50}, {"time": 9350, "pitch": 66, "duration": 170, "velocity": 50}, {"time": 9417, "pitch": 68, "duration": 102, "velocity": 62}, {"time": 9503, "pitch": 73, "duration": 212, "velocity": 86}, {"time": 9526, "pitch": 37, "duration": 2796, "velocity": 66}, {"time": 9682, "pitch": 44, "duration": 2644, "velocity": 54}, {"time": 9721, "pitch": 73, "duration": 309, "velocity": 48}, {"time": 9856, "pitch": 49, "duration": 696, "velocity": 54}, {"time": 10036, "pitch": 73, "duration": 2285, "velocity": 48}, {"time": 10041, "pitch": 66, "duration": 165, "velocity": 51}, {"time": 10214, "pitch": 71, "duration": 338, "velocity": 77}, {"time": 10216, "pitch": 66, "duration": 489, "velocity": 58}, {"time": 10385, "pitch": 70, "duration": 320, "velocity": 65}, {"time": 10556, "pitch": 71, "duration": 1767, "velocity": 60}, {"time": 10558, "pitch": 68, "duration": 1691, "velocity": 65}, {"time": 10560, "pitch": 49, "duration": 1762, "velocity": 53}, {"time": 10715, "pitch": 70, "duration": 490, "velocity": 54}, {"time": 10716, "pitch": 66, "duration": 181, "velocity": 57}, {"time": 10900, "pitch": 35, "duration": 1441, "velocity": 63}, {"time": 10902, "pitch": 66, "duration": 180, "velocity": 73}, {"time": 11073, "pitch": 42, "duration": 1249, "velocity": 48}, {"time": 11087, "pitch": 66, "duration": 133, "velocity": 38}, {"time": 11215, "pitch": 70, "duration": 1103, "velocity": 37}, {"time": 11225, "pitch": 66, "duration": 940, "velocity": 40}, {"time": 11269, "pitch": 47, "duration": 1072, "velocity": 54}, {"time": 11431, "pitch": 54, "duration": 892, "velocity": 76}, {"time": 12176, "pitch": 66, "duration": 242, "velocity": 50}, {"time": 12259, "pitch": 68, "duration": 63, "velocity": 62}, {"time": 12323, "pitch": 70, "duration": 682, "velocity": 89}, {"time": 12328, "pitch": 39, "duration": 675, "velocity": 70}, {"time": 12491, "pitch": 46, "duration": 510, "velocity": 62}, {"time": 12667, "pitch": 51, "duration": 338, "velocity": 62}, {"time": 12668, "pitch": 61, "duration": 157, "velocity": 71}, {"time": 12832, "pitch": 68, "duration": 323, "velocity": 81}, {"time": 12834, "pitch": 61, "duration": 851, "velocity": 72}, {"time": 12998, "pitch": 37, "duration": 703, "velocity": 64}, {"time": 13160, "pitch": 68, "duration": 180, "velocity": 56}, {"time": 13164, "pitch": 44, "duration": 520, "velocity": 56}, {"time": 13168, "pitch": 66, "duration": 348, "velocity": 58}, {"time": 13341, "pitch": 49, "duration": 345, "velocity": 69}, {"time": 13344, "pitch": 68, "duration": 341, "velocity": 69}, {"time": 13520, "pitch": 70, "duration": 166, "velocity": 60}, {"time": 13521, "pitch": 66, "duration": 164, "velocity": 42}, {"time": 13690, "pitch": 66, "duration": 318, "velocity": 64}, {"time": 13692, "pitch": 35, "duration": 316, "velocity": 58}, {"time": 13693, "pitch": 47, "duration": 307, "velocity": 53}, {"time": 13696, "pitch": 61, "duration": 1233, "velocity": 53}, {"time": 13834, "pitch": 42, "duration": 1217, "velocity": 49}, {"time": 14010, "pitch": 47, "duration": 750, "velocity": 61}, {"time": 14017, "pitch": 35, "duration": 1034, "velocity": 50}, {"time": 14019, "pitch": 66, "duration": 910, "velocity": 51}, {"time": 14042, "pitch": 63, "duration": 4, "velocity": 30}, {"time": 14220, "pitch": 59, "duration": 831, "velocity": 62}, {"time": 14573, "pitch": 54, "duration": 479, "velocity": 53}, {"time": 14765, "pitch": 47, "duration": 286, "velocity": 44}, {"time": 14938, "pitch": 66, "duration": 115, "velocity": 59}, {"time": 14941, "pitch": 61, "duration": 395, "velocity": 44}, {"time": 14941, "pitch": 97, "duration": 11, "velocity": 50}, {"time": 15029, "pitch": 68, "duration": 569, "velocity": 64}, {"time": 15098, "pitch": 39, "duration": 636, "velocity": 72}, {"time": 15101, "pitch": 70, "duration": 632, "velocity": 90}, {"time": 15265, "pitch": 46, "duration": 468, "velocity": 60}, {"time": 15443, "pitch": 51, "duration": 291, "velocity": 63}, {"time": 15447, "pitch": 61, "duration": 151, "velocity": 62}, {"time": 15609, "pitch": 61, "duration": 519, "velocity": 70}, {"time": 15609, "pitch": 68, "duration": 350, "velocity": 82}, {"time": 15776, "pitch": 37, "duration": 670, "velocity": 67}, {"time": 15938, "pitch": 44, "duration": 509, "velocity": 60}, {"time": 15965, "pitch": 66, "duration": 186, "velocity": 63}, {"time": 15965, "pitch": 68, "duration": 339, "velocity": 52}, {"time": 16131, "pitch": 49, "duration": 316, "velocity": 62}, {"time": 16132, "pitch": 73, "duration": 315, "velocity": 79}, {"time": 16136, "pitch": 61, "duration": 329, "velocity": 64}, {"time": 16161, "pitch": 66, "duration": 128, "velocity": 38}, {"time": 16297, "pitch": 66, "duration": 176, "velocity": 62}, {"time": 16470, "pitch": 35, "duration": 1390, "velocity": 68}, {"time": 16475, "pitch": 61, "duration": 904, "velocity": 78}, {"time": 16477, "pitch": 66, "duration": 534, "velocity": 81}, {"time": 16637, "pitch": 42, "duration": 1222, "velocity": 57}, {"time": 16826, "pitch": 47, "duration": 745, "velocity": 66}, {"time": 16838, "pitch": 59, "duration": 173, "velocity": 60}, {"time": 17015, "pitch": 63, "duration": 846, "velocity": 67}, {"time": 17016, "pitch": 59, "duration": 724, "velocity": 73}, {"time": 17016, "pitch": 66, "duration": 740, "velocity": 62}, {"time": 17384, "pitch": 61, "duration": 476, "velocity": 59}, {"time": 17581, "pitch": 47, "duration": 278, "velocity": 56}, {"time": 17749, "pitch": 59, "duration": 110, "velocity": 44}, {"time": 17765, "pitch": 66, "duration": 96, "velocity": 61}, {"time": 17766, "pitch": 97, "duration": 5, "velocity": 55}, {"time": 17845, "pitch": 99, "duration": 11, "velocity": 58}, {"time": 17846, "pitch": 68, "duration": 96, "velocity": 67}, {"time": 17910, "pitch": 70, "duration": 191, "velocity": 93}, {"time": 17913, "pitch": 39, "duration": 695, "velocity": 66}, {"time": 18100, "pitch": 46, "duration": 500, "velocity": 58}, {"time": 18110, "pitch": 70, "duration": 479, "velocity": 56}, {"time": 18257, "pitch": 51, "duration": 332, "velocity": 69}, {"time": 18259, "pitch": 61, "duration": 173, "velocity": 66}, {"time": 18437, "pitch": 61, "duration": 855, "velocity": 71}, {"time": 18437, "pitch": 68, "duration": 509, "velocity": 82}, {"time": 18597, "pitch": 37, "duration": 710, "velocity": 68}, {"time": 18763, "pitch": 44, "duration": 522, "velocity": 55}, {"time": 18772, "pitch": 66, "duration": 512, "velocity": 61}, {"time": 18957, "pitch": 49, "duration": 330, "velocity": 64}, {"time": 18957, "pitch": 68, "duration": 330, "velocity": 67}, {"time": 19119, "pitch": 70, "duration": 168, "velocity": 69}, {"time": 19290, "pitch": 66, "duration": 539, "velocity": 65}, {"time": 19291, "pitch": 35, "duration": 1421, "velocity": 64}, {"time": 19296, "pitch": 61, "duration": 526, "velocity": 64}, {"time": 19453, "pitch": 42, "duration": 1241, "velocity": 58}, {"time": 19649, "pitch": 47, "duration": 710, "velocity": 62}, {"time": 19830, "pitch": 61, "duration": 863, "velocity": 65}, {"time": 19834, "pitch": 63, "duration": 855, "velocity": 65}, {"time": 19835, "pitch": 66, "duration": 859, "velocity": 63}, {"time": 19836, "pitch": 59, "duration": 339, "velocity": 66}, {"time": 20186, "pitch": 59, "duration": 508, "velocity": 63}, {"time": 20369, "pitch": 47, "duration": 324, "velocity": 62}, {"time": 20534, "pitch": 68, "duration": 1400, "velocity": 61}, {"time": 20535, "pitch": 56, "duration": 147, "velocity": 69}, {"time": 20693, "pitch": 56, "duration": 549, "velocity": 75}, {"time": 20698, "pitch": 63, "duration": 882, "velocity": 71}, {"time": 20705, "pitch": 32, "duration": 438, "velocity": 67}, {"time": 20706, "pitch": 60, "duration": 721, "velocity": 78}, {"time": 20897, "pitch": 44, "duration": 345, "velocity": 70}, {"time": 21079, "pitch": 54, "duration": 2475, "velocity": 63}, {"time": 21248, "pitch": 56, "duration": 2314, "velocity": 69}, {"time": 21252, "pitch": 44, "duration": 520, "velocity": 65}, {"time": 21437, "pitch": 60, "duration": 351, "velocity": 67}, {"time": 21590, "pitch": 63, "duration": 858, "velocity": 71}, {"time": 21781, "pitch": 44, "duration": 828, "velocity": 63}, {"time": 21782, "pitch": 66, "duration": 1357, "velocity": 65}, {"time": 21796, "pitch": 60, "duration": 499, "velocity": 45}, {"time": 21940, "pitch": 68, "duration": 669, "velocity": 69}, {"time": 22114, "pitch": 32, "duration": 1448, "velocity": 73}, {"time": 22115, "pitch": 70, "duration": 325, "velocity": 88}, {"time": 22299, "pitch": 60, "duration": 510, "velocity": 65}, {"time": 22451, "pitch": 70, "duration": 1057, "velocity": 69}, {"time": 22452, "pitch": 63, "duration": 503, "velocity": 69}, {"time": 22620, "pitch": 68, "duration": 704, "velocity": 87}, {"time": 22621, "pitch": 44, "duration": 342, "velocity": 65}, {"time": 22816, "pitch": 60, "duration": 746, "velocity": 55}, {"time": 22966, "pitch": 63, "duration": 579, "velocity": 60}, {"time": 22967, "pitch": 44, "duration": 172, "velocity": 47}, {"time": 23147, "pitch": 44, "duration": 398, "velocity": 64}, {"time": 23148, "pitch": 97, "duration": 7, "velocity": 63}, {"time": 23150, "pitch": 66, "duration": 174, "velocity": 65}, {"time": 23330, "pitch": 61, "duration": 214, "velocity": 67}, {"time": 23333, "pitch": 68, "duration": 212, "velocity": 59}, {"time": 23334, "pitch": 66, "duration": 1626, "velocity": 53}, {"time": 23513, "pitch": 37, "duration": 284, "velocity": 69}, {"time": 23514, "pitch": 70, "duration": 4610, "velocity": 78}, {"time": 23686, "pitch": 61, "duration": 4607, "velocity": 55}], "annotations": [{"time": 7, "annotation": {"number": 64, "value": 127}, "group": "control_change"}, {"time": 1055, "annotation": {"number": 64, "value": 0}, "group": "control_change"}, {"time": 1251, "annotation": {"number": 64, "value": 127}, "group": "control_change"}, {"time": 2454, "annotation": {"number": 64, "value": 0}, "group": "control_change"}, {"time": 2549, "annotation": {"number": 64, "value": 127}, "group": "control_change"}, {"time": 3867, "annotation": {"number": 64, "value": 0}, "group": "control_change"}, {"time": 4032, "annotation": {"number": 64, "value": 127}, "group": "control_change"}, {"time": 5288, "annotation": {"number": 64, "value": 0}, "group": "control_change"}, {"time": 5399, "annotation": {"number": 64, "value": 127}, "group": "control_change"}, {"time": 6679, "annotation": {"number": 64, "value": 0}, "group": "control_change"}, {"time": 6781, "annotation": {"number": 64, "value": 127}, "group": "control_change"}, {"time": 8070, "annotation": {"number": 64, "value": 0}, "group": "control_change"}, {"time": 8125, "annotation": {"number": 64, "value": 127}, "group": "control_change"}, {"time": 9519, "annotation": {"number": 64, "value": 0}, "group": "control_change"}, {"time": 9584, "annotation": {"number": 64, "value": 127}, "group": "control_change"}, {"time": 12329, "annotation": {"number": 64, "value": 0}, "group": "control_change"}, {"time": 12410, "annotation": {"number": 64, "value": 127}, "group": "control_change"}, {"time": 12997, "annotation": {"number": 64, "value": 0}, "group": "control_change"}, {"time": 13071, "annotation": {"number": 64, "value": 127}, "group": "control_change"}, {"time": 13689, "annotation": {"number": 64, "value": 0}, "group": "control_change"}, {"time": 13785, "annotation": {"number": 64, "value": 127}, "group": "control_change"}, {"time": 15057, "annotation": {"number": 64, "value": 0}, "group": "control_change"}, {"time": 15183, "annotation": {"number": 64, "value": 127}, "group": "control_change"}, {"time": 15732, "annotation": {"number": 64, "value": 0}, "group": "control_change"}, {"time": 15820, "annotation": {"number": 64, "value": 127}, "group": "control_change"}, {"time": 16447, "annotation": {"number": 64, "value": 0}, "group": "control_change"}, {"time": 16550, "annotation": {"number": 64, "value": 127}, "group": "control_change"}, {"time": 17861, "annotation": {"number": 64, "value": 0}, "group": "control_change"}, {"time": 17978, "annotation": {"number": 64, "value": 127}, "group": "control_change"}, {"time": 18589, "annotation": {"number": 64, "value": 0}, "group": "control_change"}, {"time": 18677, "annotation": {"number": 64, "value": 127}, "group": "control_change"}, {"time": 19288, "annotation": {"number": 64, "value": 0}, "group": "control_change"}, {"time": 19368, "annotation": {"number": 64, "value": 127}, "group": "control_change"}, {"time": 20695, "annotation": {"number": 64, "value": 0}, "group": "control_change"}, {"time": 20805, "annotation": {"number": 64, "value": 127}, "group": "control_change"}, {"time": 22139, "annotation": {"number": 64, "value": 0}, "group": "control_change"}, {"time": 22179, "annotation": {"number": 64, "value": 127}, "group": "control_change"}, {"time": 23545, "annotation": {"number": 64, "value": 0}, "group": "control_change"}, {"time": 23639, "annotation": {"number": 64, "value": 127}, "group": "control_change"}, {"time": 23798, "annotation": {"number": 64, "value": 0}, "group": "control_change"}, {"time": 24460, "annotation": {"number": 64, "value": 127}, "group": "control_change"}, {"time": 24960, "annotation": {"number": 64, "value": 0}, "group": "control_change"}]}]}