{"metadata": {"schema_version": "0.2", "title": "None", "source_filename": "Q4_HYVmgq5Y93g_0.mid", "source_format": "midi"}, "resolution": 384, "tempos": [{"time": 0, "qpm": 120.0}], "time_signatures": [{"time": 0, "numerator": 4, "denominator": 4}], "annotations": [{"time": 0, "annotation": {"emo_class": "4", "YouTube_ID": "HYVmgq5Y93g", "seg_id": "0"}}], "tracks": [{"program": 0, "is_drum": false, "notes": [{"time": 64, "pitch": 52, "duration": 1341, "velocity": 39}, {"time": 65, "pitch": 68, "duration": 833, "velocity": 61}, {"time": 489, "pitch": 59, "duration": 893, "velocity": 42}, {"time": 717, "pitch": 64, "duration": 2086, "velocity": 49}, {"time": 905, "pitch": 68, "duration": 455, "velocity": 69}, {"time": 1124, "pitch": 71, "duration": 246, "velocity": 76}, {"time": 1370, "pitch": 57, "duration": 1422, "velocity": 43}, {"time": 1375, "pitch": 73, "duration": 713, "velocity": 51}, {"time": 1608, "pitch": 76, "duration": 1179, "velocity": 62}, {"time": 2096, "pitch": 73, "duration": 696, "velocity": 52}, {"time": 2551, "pitch": 71, "duration": 246, "velocity": 52}, {"time": 2806, "pitch": 61, "duration": 970, "velocity": 33}, {"time": 2806, "pitch": 68, "duration": 969, "velocity": 40}, {"time": 2807, "pitch": 64, "duration": 967, "velocity": 40}, {"time": 3773, "pitch": 63, "duration": 491, "velocity": 35}, {"time": 3774, "pitch": 54, "duration": 565, "velocity": 29}, {"time": 4259, "pitch": 56, "duration": 1581, "velocity": 31}, {"time": 4259, "pitch": 64, "duration": 1570, "velocity": 35}, {"time": 4327, "pitch": 61, "duration": 1502, "velocity": 30}, {"time": 5818, "pitch": 45, "duration": 1341, "velocity": 38}, {"time": 5822, "pitch": 57, "duration": 1358, "velocity": 37}, {"time": 5825, "pitch": 69, "duration": 925, "velocity": 43}, {"time": 5833, "pitch": 61, "duration": 641, "velocity": 35}, {"time": 5834, "pitch": 64, "duration": 855, "velocity": 37}, {"time": 6478, "pitch": 61, "duration": 925, "velocity": 42}, {"time": 6700, "pitch": 64, "duration": 1187, "velocity": 49}, {"time": 6908, "pitch": 69, "duration": 242, "velocity": 59}, {"time": 7160, "pitch": 69, "duration": 234, "velocity": 81}, {"time": 7401, "pitch": 68, "duration": 424, "velocity": 54}, {"time": 7836, "pitch": 68, "duration": 706, "velocity": 78}, {"time": 8264, "pitch": 64, "duration": 301, "velocity": 47}, {"time": 8571, "pitch": 47, "duration": 2439, "velocity": 33}, {"time": 8573, "pitch": 66, "duration": 2440, "velocity": 36}, {"time": 8574, "pitch": 63, "duration": 2477, "velocity": 32}, {"time": 8597, "pitch": 59, "duration": 1455, "velocity": 28}, {"time": 11006, "pitch": 59, "duration": 949, "velocity": 40}, {"time": 11225, "pitch": 66, "duration": 280, "velocity": 45}, {"time": 11487, "pitch": 40, "duration": 155, "velocity": 39}, {"time": 11488, "pitch": 52, "duration": 1107, "velocity": 40}, {"time": 11488, "pitch": 68, "duration": 892, "velocity": 50}, {"time": 11956, "pitch": 64, "duration": 2259, "velocity": 45}, {"time": 12390, "pitch": 68, "duration": 476, "velocity": 52}, {"time": 12391, "pitch": 56, "duration": 474, "velocity": 44}, {"time": 12602, "pitch": 40, "duration": 264, "velocity": 31}, {"time": 12604, "pitch": 52, "duration": 4509, "velocity": 30}, {"time": 12604, "pitch": 71, "duration": 267, "velocity": 65}, {"time": 12855, "pitch": 45, "duration": 9, "velocity": 53}, {"time": 12861, "pitch": 57, "duration": 1344, "velocity": 54}, {"time": 12867, "pitch": 73, "duration": 642, "velocity": 85}, {"time": 13094, "pitch": 76, "duration": 753, "velocity": 72}, {"time": 13520, "pitch": 73, "duration": 626, "velocity": 78}, {"time": 13942, "pitch": 71, "duration": 263, "velocity": 69}, {"time": 14191, "pitch": 68, "duration": 1407, "velocity": 72}, {"time": 14210, "pitch": 61, "duration": 1441, "velocity": 42}, {"time": 14220, "pitch": 64, "duration": 1454, "velocity": 38}, {"time": 15135, "pitch": 54, "duration": 519, "velocity": 26}, {"time": 15166, "pitch": 63, "duration": 484, "velocity": 36}, {"time": 15607, "pitch": 68, "duration": 1097, "velocity": 14}, {"time": 15633, "pitch": 56, "duration": 1482, "velocity": 29}, {"time": 15680, "pitch": 64, "duration": 1433, "velocity": 34}, {"time": 17104, "pitch": 45, "duration": 1358, "velocity": 35}, {"time": 17106, "pitch": 57, "duration": 442, "velocity": 41}, {"time": 17106, "pitch": 69, "duration": 464, "velocity": 42}, {"time": 17554, "pitch": 57, "duration": 885, "velocity": 44}, {"time": 17773, "pitch": 61, "duration": 692, "velocity": 47}, {"time": 17988, "pitch": 64, "duration": 1565, "velocity": 58}, {"time": 18191, "pitch": 69, "duration": 264, "velocity": 79}, {"time": 18459, "pitch": 69, "duration": 222, "velocity": 76}, {"time": 18688, "pitch": 68, "duration": 435, "velocity": 74}, {"time": 19129, "pitch": 68, "duration": 729, "velocity": 52}, {"time": 19594, "pitch": 64, "duration": 294, "velocity": 46}, {"time": 19896, "pitch": 66, "duration": 2514, "velocity": 37}, {"time": 19910, "pitch": 47, "duration": 1821, "velocity": 37}, {"time": 19912, "pitch": 63, "duration": 2813, "velocity": 30}, {"time": 19923, "pitch": 59, "duration": 866, "velocity": 28}, {"time": 20322, "pitch": 54, "duration": 1842, "velocity": 30}, {"time": 20796, "pitch": 59, "duration": 923, "velocity": 37}, {"time": 21252, "pitch": 51, "duration": 1475, "velocity": 39}, {"time": 21728, "pitch": 59, "duration": 697, "velocity": 43}, {"time": 22175, "pitch": 54, "duration": 551, "velocity": 31}, {"time": 22430, "pitch": 59, "duration": 279, "velocity": 49}, {"time": 22706, "pitch": 68, "duration": 863, "velocity": 51}, {"time": 22715, "pitch": 40, "duration": 117, "velocity": 41}, {"time": 22717, "pitch": 52, "duration": 1344, "velocity": 42}, {"time": 22720, "pitch": 59, "duration": 404, "velocity": 38}, {"time": 23134, "pitch": 59, "duration": 405, "velocity": 50}, {"time": 23340, "pitch": 64, "duration": 702, "velocity": 53}, {"time": 23563, "pitch": 56, "duration": 479, "velocity": 47}, {"time": 23573, "pitch": 68, "duration": 469, "velocity": 77}, {"time": 23770, "pitch": 71, "duration": 271, "velocity": 77}, {"time": 24036, "pitch": 45, "duration": 1324, "velocity": 49}, {"time": 24041, "pitch": 57, "duration": 1316, "velocity": 49}, {"time": 24043, "pitch": 73, "duration": 632, "velocity": 76}, {"time": 24262, "pitch": 76, "duration": 1098, "velocity": 90}, {"time": 24680, "pitch": 73, "duration": 676, "velocity": 63}, {"time": 24893, "pitch": 64, "duration": 1449, "velocity": 49}, {"time": 25094, "pitch": 71, "duration": 263, "velocity": 78}, {"time": 25383, "pitch": 68, "duration": 964, "velocity": 53}, {"time": 25847, "pitch": 56, "duration": 1025, "velocity": 32}, {"time": 25851, "pitch": 52, "duration": 2534, "velocity": 31}, {"time": 26317, "pitch": 33, "duration": 10, "velocity": 27}, {"time": 26325, "pitch": 54, "duration": 582, "velocity": 27}, {"time": 26342, "pitch": 63, "duration": 565, "velocity": 35}, {"time": 26881, "pitch": 56, "duration": 1491, "velocity": 23}, {"time": 26900, "pitch": 64, "duration": 1473, "velocity": 27}, {"time": 28416, "pitch": 57, "duration": 253, "velocity": 36}, {"time": 28417, "pitch": 45, "duration": 813, "velocity": 35}, {"time": 28442, "pitch": 69, "duration": 619, "velocity": 40}, {"time": 28886, "pitch": 57, "duration": 889, "velocity": 44}, {"time": 29077, "pitch": 61, "duration": 686, "velocity": 47}, {"time": 29290, "pitch": 64, "duration": 474, "velocity": 78}, {"time": 29511, "pitch": 69, "duration": 241, "velocity": 58}, {"time": 29758, "pitch": 69, "duration": 263, "velocity": 83}, {"time": 29999, "pitch": 68, "duration": 429, "velocity": 68}, {"time": 30432, "pitch": 68, "duration": 685, "velocity": 67}, {"time": 30657, "pitch": 59, "duration": 1952, "velocity": 35}, {"time": 30661, "pitch": 52, "duration": 461, "velocity": 25}, {"time": 30890, "pitch": 64, "duration": 230, "velocity": 43}, {"time": 31117, "pitch": 66, "duration": 1254, "velocity": 45}, {"time": 31147, "pitch": 47, "duration": 909, "velocity": 33}, {"time": 31563, "pitch": 54, "duration": 493, "velocity": 31}, {"time": 31567, "pitch": 51, "duration": 489, "velocity": 23}, {"time": 32061, "pitch": 54, "duration": 963, "velocity": 29}, {"time": 32065, "pitch": 51, "duration": 505, "velocity": 23}, {"time": 32066, "pitch": 47, "duration": 581, "velocity": 24}, {"time": 32579, "pitch": 44, "duration": 45, "velocity": 32}, {"time": 32580, "pitch": 51, "duration": 1534, "velocity": 35}, {"time": 32598, "pitch": 66, "duration": 932, "velocity": 40}, {"time": 32614, "pitch": 59, "duration": 410, "velocity": 41}, {"time": 33033, "pitch": 54, "duration": 1069, "velocity": 31}, {"time": 33033, "pitch": 59, "duration": 720, "velocity": 30}, {"time": 33542, "pitch": 66, "duration": 563, "velocity": 45}, {"time": 33764, "pitch": 59, "duration": 189, "velocity": 46}, {"time": 33963, "pitch": 59, "duration": 140, "velocity": 23}, {"time": 34066, "pitch": 68, "duration": 1323, "velocity": 55}, {"time": 34097, "pitch": 52, "duration": 2106, "velocity": 35}, {"time": 34512, "pitch": 56, "duration": 862, "velocity": 72}, {"time": 34736, "pitch": 59, "duration": 640, "velocity": 65}, {"time": 34970, "pitch": 64, "duration": 1248, "velocity": 59}, {"time": 35162, "pitch": 71, "duration": 217, "velocity": 55}, {"time": 35408, "pitch": 73, "duration": 657, "velocity": 83}, {"time": 35409, "pitch": 57, "duration": 1316, "velocity": 51}, {"time": 35652, "pitch": 76, "duration": 431, "velocity": 87}, {"time": 36070, "pitch": 73, "duration": 658, "velocity": 79}, {"time": 36289, "pitch": 61, "duration": 439, "velocity": 55}, {"time": 36509, "pitch": 71, "duration": 218, "velocity": 64}, {"time": 36778, "pitch": 68, "duration": 1476, "velocity": 64}, {"time": 36782, "pitch": 71, "duration": 5, "velocity": 45}, {"time": 37211, "pitch": 52, "duration": 2609, "velocity": 29}, {"time": 37221, "pitch": 61, "duration": 1040, "velocity": 35}, {"time": 37226, "pitch": 44, "duration": 2571, "velocity": 33}, {"time": 37226, "pitch": 49, "duration": 490, "velocity": 30}, {"time": 37230, "pitch": 56, "duration": 978, "velocity": 31}, {"time": 37705, "pitch": 42, "duration": 564, "velocity": 37}, {"time": 37705, "pitch": 54, "duration": 550, "velocity": 32}, {"time": 37712, "pitch": 63, "duration": 551, "velocity": 40}, {"time": 37725, "pitch": 49, "duration": 1635, "velocity": 23}, {"time": 38218, "pitch": 56, "duration": 1595, "velocity": 26}, {"time": 38267, "pitch": 64, "duration": 1215, "velocity": 35}, {"time": 38268, "pitch": 61, "duration": 1268, "velocity": 20}, {"time": 39256, "pitch": 47, "duration": 226, "velocity": 32}, {"time": 39489, "pitch": 47, "duration": 335, "velocity": 31}, {"time": 39494, "pitch": 64, "duration": 856, "velocity": 42}, {"time": 39844, "pitch": 45, "duration": 460, "velocity": 38}, {"time": 39848, "pitch": 69, "duration": 886, "velocity": 44}, {"time": 39849, "pitch": 61, "duration": 593, "velocity": 37}, {"time": 40309, "pitch": 45, "duration": 656, "velocity": 38}, {"time": 40316, "pitch": 57, "duration": 925, "velocity": 48}, {"time": 40533, "pitch": 61, "duration": 687, "velocity": 59}, {"time": 40751, "pitch": 64, "duration": 590, "velocity": 51}, {"time": 40950, "pitch": 69, "duration": 260, "velocity": 69}, {"time": 41215, "pitch": 69, "duration": 233, "velocity": 80}, {"time": 41448, "pitch": 68, "duration": 400, "velocity": 85}, {"time": 41854, "pitch": 68, "duration": 702, "velocity": 60}, {"time": 42087, "pitch": 59, "duration": 1896, "velocity": 38}, {"time": 42306, "pitch": 64, "duration": 251, "velocity": 50}, {"time": 42566, "pitch": 47, "duration": 1404, "velocity": 40}, {"time": 42566, "pitch": 63, "duration": 1404, "velocity": 42}, {"time": 42571, "pitch": 66, "duration": 1400, "velocity": 47}, {"time": 43023, "pitch": 54, "duration": 947, "velocity": 35}, {"time": 44002, "pitch": 56, "duration": 1125, "velocity": 35}, {"time": 44005, "pitch": 68, "duration": 1300, "velocity": 39}, {"time": 44060, "pitch": 63, "duration": 2012, "velocity": 29}, {"time": 44064, "pitch": 48, "duration": 1240, "velocity": 32}, {"time": 44068, "pitch": 60, "duration": 2004, "velocity": 30}, {"time": 45135, "pitch": 56, "duration": 937, "velocity": 28}], "annotations": [{"time": 138, "annotation": {"number": 64, "value": 127}, "group": "control_change"}, {"time": 606, "annotation": {"number": 64, "value": 0}, "group": "control_change"}, {"time": 714, "annotation": {"number": 64, "value": 127}, "group": "control_change"}, {"time": 1297, "annotation": {"number": 64, "value": 0}, "group": "control_change"}, {"time": 1520, "annotation": {"number": 64, "value": 127}, "group": "control_change"}, {"time": 2119, "annotation": {"number": 64, "value": 0}, "group": "control_change"}, {"time": 2250, "annotation": {"number": 64, "value": 127}, "group": "control_change"}, {"time": 2734, "annotation": {"number": 64, "value": 0}, "group": "control_change"}, {"time": 3202, "annotation": {"number": 64, "value": 127}, "group": "control_change"}, {"time": 3773, "annotation": {"number": 64, "value": 0}, "group": "control_change"}, {"time": 3878, "annotation": {"number": 64, "value": 127}, "group": "control_change"}, {"time": 4329, "annotation": {"number": 64, "value": 0}, "group": "control_change"}, {"time": 4561, "annotation": {"number": 64, "value": 127}, "group": "control_change"}, {"time": 5816, "annotation": {"number": 64, "value": 0}, "group": "control_change"}, {"time": 5921, "annotation": {"number": 64, "value": 127}, "group": "control_change"}, {"time": 7162, "annotation": {"number": 64, "value": 0}, "group": "control_change"}, {"time": 7319, "annotation": {"number": 64, "value": 127}, "group": "control_change"}, {"time": 7357, "annotation": {"number": 64, "value": 0}, "group": "control_change"}, {"time": 7472, "annotation": {"number": 64, "value": 127}, "group": "control_change"}, {"time": 7845, "annotation": {"number": 64, "value": 0}, "group": "control_change"}, {"time": 7918, "annotation": {"number": 64, "value": 127}, "group": "control_change"}, {"time": 8581, "annotation": {"number": 64, "value": 0}, "group": "control_change"}, {"time": 8755, "annotation": {"number": 64, "value": 127}, "group": "control_change"}, {"time": 11112, "annotation": {"number": 64, "value": 0}, "group": "control_change"}, {"time": 11205, "annotation": {"number": 64, "value": 127}, "group": "control_change"}, {"time": 11500, "annotation": {"number": 64, "value": 0}, "group": "control_change"}, {"time": 11619, "annotation": {"number": 64, "value": 127}, "group": "control_change"}, {"time": 12399, "annotation": {"number": 64, "value": 0}, "group": "control_change"}, {"time": 12449, "annotation": {"number": 64, "value": 127}, "group": "control_change"}, {"time": 12868, "annotation": {"number": 64, "value": 0}, "group": "control_change"}, {"time": 12917, "annotation": {"number": 64, "value": 127}, "group": "control_change"}, {"time": 13527, "annotation": {"number": 64, "value": 0}, "group": "control_change"}, {"time": 13639, "annotation": {"number": 64, "value": 127}, "group": "control_change"}, {"time": 13954, "annotation": {"number": 64, "value": 0}, "group": "control_change"}, {"time": 14039, "annotation": {"number": 64, "value": 127}, "group": "control_change"}, {"time": 14196, "annotation": {"number": 64, "value": 0}, "group": "control_change"}, {"time": 14300, "annotation": {"number": 64, "value": 127}, "group": "control_change"}, {"time": 15652, "annotation": {"number": 64, "value": 0}, "group": "control_change"}, {"time": 15843, "annotation": {"number": 64, "value": 127}, "group": "control_change"}, {"time": 17115, "annotation": {"number": 64, "value": 0}, "group": "control_change"}, {"time": 17218, "annotation": {"number": 64, "value": 127}, "group": "control_change"}, {"time": 17563, "annotation": {"number": 64, "value": 0}, "group": "control_change"}, {"time": 17633, "annotation": {"number": 64, "value": 127}, "group": "control_change"}, {"time": 18451, "annotation": {"number": 64, "value": 0}, "group": "control_change"}, {"time": 18539, "annotation": {"number": 64, "value": 127}, "group": "control_change"}, {"time": 18676, "annotation": {"number": 64, "value": 0}, "group": "control_change"}, {"time": 18723, "annotation": {"number": 64, "value": 127}, "group": "control_change"}, {"time": 19861, "annotation": {"number": 64, "value": 0}, "group": "control_change"}, {"time": 20083, "annotation": {"number": 64, "value": 127}, "group": "control_change"}, {"time": 22718, "annotation": {"number": 64, "value": 0}, "group": "control_change"}, {"time": 22848, "annotation": {"number": 64, "value": 127}, "group": "control_change"}, {"time": 23231, "annotation": {"number": 64, "value": 0}, "group": "control_change"}, {"time": 23262, "annotation": {"number": 64, "value": 127}, "group": "control_change"}, {"time": 23331, "annotation": {"number": 64, "value": 0}, "group": "control_change"}, {"time": 23362, "annotation": {"number": 64, "value": 127}, "group": "control_change"}, {"time": 23573, "annotation": {"number": 64, "value": 0}, "group": "control_change"}, {"time": 23608, "annotation": {"number": 64, "value": 127}, "group": "control_change"}, {"time": 24047, "annotation": {"number": 64, "value": 0}, "group": "control_change"}, {"time": 24253, "annotation": {"number": 64, "value": 127}, "group": "control_change"}, {"time": 25354, "annotation": {"number": 64, "value": 0}, "group": "control_change"}, {"time": 25505, "annotation": {"number": 64, "value": 127}, "group": "control_change"}, {"time": 26357, "annotation": {"number": 64, "value": 0}, "group": "control_change"}, {"time": 26449, "annotation": {"number": 64, "value": 127}, "group": "control_change"}, {"time": 26909, "annotation": {"number": 64, "value": 0}, "group": "control_change"}, {"time": 27056, "annotation": {"number": 64, "value": 127}, "group": "control_change"}, {"time": 28405, "annotation": {"number": 64, "value": 0}, "group": "control_change"}, {"time": 28523, "annotation": {"number": 64, "value": 127}, "group": "control_change"}, {"time": 28890, "annotation": {"number": 64, "value": 0}, "group": "control_change"}, {"time": 28938, "annotation": {"number": 64, "value": 127}, "group": "control_change"}, {"time": 29289, "annotation": {"number": 64, "value": 0}, "group": "control_change"}, {"time": 29329, "annotation": {"number": 64, "value": 127}, "group": "control_change"}, {"time": 29763, "annotation": {"number": 64, "value": 0}, "group": "control_change"}, {"time": 29844, "annotation": {"number": 64, "value": 127}, "group": "control_change"}, {"time": 29996, "annotation": {"number": 64, "value": 0}, "group": "control_change"}, {"time": 30074, "annotation": {"number": 64, "value": 127}, "group": "control_change"}, {"time": 31019, "annotation": {"number": 64, "value": 0}, "group": "control_change"}, {"time": 31288, "annotation": {"number": 64, "value": 127}, "group": "control_change"}, {"time": 32117, "annotation": {"number": 64, "value": 0}, "group": "control_change"}, {"time": 32209, "annotation": {"number": 64, "value": 127}, "group": "control_change"}, {"time": 32601, "annotation": {"number": 64, "value": 0}, "group": "control_change"}, {"time": 32724, "annotation": {"number": 64, "value": 127}, "group": "control_change"}, {"time": 34101, "annotation": {"number": 64, "value": 0}, "group": "control_change"}, {"time": 34214, "annotation": {"number": 64, "value": 127}, "group": "control_change"}, {"time": 34516, "annotation": {"number": 64, "value": 0}, "group": "control_change"}, {"time": 34567, "annotation": {"number": 64, "value": 127}, "group": "control_change"}, {"time": 35408, "annotation": {"number": 64, "value": 0}, "group": "control_change"}, {"time": 35443, "annotation": {"number": 64, "value": 127}, "group": "control_change"}, {"time": 36742, "annotation": {"number": 64, "value": 0}, "group": "control_change"}, {"time": 36802, "annotation": {"number": 64, "value": 127}, "group": "control_change"}, {"time": 38263, "annotation": {"number": 64, "value": 0}, "group": "control_change"}, {"time": 38446, "annotation": {"number": 64, "value": 127}, "group": "control_change"}, {"time": 39849, "annotation": {"number": 64, "value": 0}, "group": "control_change"}, {"time": 39959, "annotation": {"number": 64, "value": 127}, "group": "control_change"}, {"time": 40761, "annotation": {"number": 64, "value": 0}, "group": "control_change"}, {"time": 40880, "annotation": {"number": 64, "value": 127}, "group": "control_change"}, {"time": 41222, "annotation": {"number": 64, "value": 0}, "group": "control_change"}, {"time": 41295, "annotation": {"number": 64, "value": 127}, "group": "control_change"}, {"time": 41446, "annotation": {"number": 64, "value": 0}, "group": "control_change"}, {"time": 41495, "annotation": {"number": 64, "value": 127}, "group": "control_change"}, {"time": 41860, "annotation": {"number": 64, "value": 0}, "group": "control_change"}, {"time": 41917, "annotation": {"number": 64, "value": 127}, "group": "control_change"}, {"time": 42559, "annotation": {"number": 64, "value": 0}, "group": "control_change"}, {"time": 42831, "annotation": {"number": 64, "value": 127}, "group": "control_change"}, {"time": 42892, "annotation": {"number": 64, "value": 0}, "group": "control_change"}, {"time": 43000, "annotation": {"number": 64, "value": 127}, "group": "control_change"}, {"time": 43979, "annotation": {"number": 64, "value": 0}, "group": "control_change"}, {"time": 44305, "annotation": {"number": 64, "value": 127}, "group": "control_change"}, {"time": 45307, "annotation": {"number": 64, "value": 0}, "group": "control_change"}]}]}